gopher/__init__.py
gopher/binary_comparison.py
gopher/custom_fit.py
gopher/dinuc_shuffle.py
gopher/filter_viz.py
gopher/global_importance.py
gopher/losses.py
gopher/metrics.py
gopher/modelzoo.py
gopher/robustness_test.py
gopher/saliency_embed.py
gopher/utils.py
gopher/variant_effect.py
gopher/wandb_train.py
bio_gopher-1.0.3.dist-info/LICENSE
bio_gopher-1.0.3.dist-info/METADATA
bio_gopher-1.0.3.dist-info/WHEEL
bio_gopher-1.0.3.dist-info/top_level.txt
bio_gopher-1.0.3.dist-info/RECORD
