Metadata-Version: 2.1
Name: bio-gopher
Version: 1.0.3
Summary: GOPHER: GenOmic Profile-model compreHensive EvaluatoR
Author-email: Shushan Toneyan <toneyan@cshl.edu>, Ziqi Tang <ztang@cshl.edu>, Peter Koo <pkoo@cshl.edu>
Project-URL: Homepage, https://github.com/shtoneyan/gopher
Classifier: Programming Language :: Python :: 3
Classifier: License :: OSI Approved :: MIT License
Classifier: Operating System :: OS Independent
Requires-Python: >=3.7
License-File: LICENSE
